gwdatafind/__init__.py
gwdatafind/__main__.py
gwdatafind/io.py
gwdatafind/ui.py
gwdatafind/utils.py
gwdatafind/api/__init__.py
gwdatafind/api/common.py
gwdatafind/api/ldr.py
gwdatafind/api/v1.py
gwdatafind/tests/__init__.py
gwdatafind/tests/test_api_ldr.py
gwdatafind/tests/test_main.py
gwdatafind/tests/test_ui.py
gwdatafind/tests/test_utils.py
gwdatafind-2.1.0.dist-info/licenses/LICENSE
gwdatafind-2.1.0.dist-info/METADATA
gwdatafind-2.1.0.dist-info/WHEEL
gwdatafind-2.1.0.dist-info/entry_points.txt
gwdatafind-2.1.0.dist-info/top_level.txt
gwdatafind-2.1.0.dist-info/RECORD
