Metadata-Version: 2.4
Name: gwdatafind
Version: 2.1.0
Summary: The GWDataFind data discovery client
Author-email: Duncan Macleod <duncan.macleod@ligo.org>
License: GPL-3.0-or-later
Project-URL: Homepage, https://gwdatafind.readthedocs.io
Project-URL: Bug Tracker, https://git.ligo.org/gwdatafind/gwdatafind/-/issues/
Project-URL: Documentation, https://gwdatafind.readthedocs.io
Project-URL: Source Code, https://git.ligo.org/gwdatafind/gwdatafind.git
Classifier: Development Status :: 5 - Production/Stable
Classifier: Intended Audience :: Science/Research
Classifier: License :: OSI Approved :: MIT License
Classifier: Natural Language :: English
Classifier: Programming Language :: Python
Classifier: Programming Language :: Python :: 3
Classifier: Programming Language :: Python :: 3.6
Classifier: Programming Language :: Python :: 3.7
Classifier: Programming Language :: Python :: 3.8
Classifier: Programming Language :: Python :: 3.9
Classifier: Programming Language :: Python :: 3.10
Classifier: Programming Language :: Python :: 3.11
Classifier: Programming Language :: Python :: 3.12
Classifier: Topic :: Scientific/Engineering
Classifier: Topic :: Scientific/Engineering :: Astronomy
Classifier: Topic :: Scientific/Engineering :: Physics
Requires-Python: >=3.9
License-File: LICENSE
Requires-Dist: igwn-auth-utils>=0.3.1
Requires-Dist: igwn-segments
Provides-Extra: docs
Requires-Dist: furo; extra == "docs"
Requires-Dist: myst-parser>=4.0.1; extra == "docs"
Requires-Dist: Sphinx>=4.4.0; extra == "docs"
Requires-Dist: sphinx-argparse; extra == "docs"
Requires-Dist: sphinx-automodapi; extra == "docs"
Requires-Dist: sphinx-copybutton; extra == "docs"
Requires-Dist: sphinx-github-style; extra == "docs"
Provides-Extra: test
Requires-Dist: pytest>=3.9.3; extra == "test"
Requires-Dist: pytest-cov; extra == "test"
Requires-Dist: requests-mock; extra == "test"
Dynamic: license-file
